README.rst
cronfed.py
setup.py
cronfed.egg-info/PKG-INFO
cronfed.egg-info/SOURCES.txt
cronfed.egg-info/dependency_links.txt
cronfed.egg-info/pbr.json
cronfed.egg-info/requires.txt
cronfed.egg-info/top_level.txt
cronfed.egg-info/zip-safe