Metadata-Version: 1.1
Name: cronfed
Version: 0.2.1
Summary: Bare minimum cron job monitoring for the masses.
Home-page: https://github.com/hatnote/cronfed
Author: Mahmoud Hashemi and Mark Williams
Author-email: mahmoudrhashemi@gmail.com
License: BSD
Platform: any
Classifier: Intended Audience :: Developers
Classifier: Topic :: Software Development :: Libraries
Classifier: Programming Language :: Python :: 2.6
Classifier: Programming Language :: Python :: 2.7
